Workbook
Name investimento_mensal: Ferramenta!$E$13
Name patrimonio_acumulado: Ferramenta!$I$12
Name periodo: Ferramenta!$E$14
Name rendimento_carteira: Ferramenta!$I$11
Name salario: Ferramenta!$E$11
Name sugestao: Ferramenta!$E$12
Name taxa_mensal: Ferramenta!$I$10

Sheet Ferramenta
C3: Calculadora de Patrimônio e Dividendos
C8: Informações Base | G8: Painel de Investimento
C10: Perfil | G10: Taxa de rendimento mensal | I10: 0.01079
C11: Salário | G11: Taxa de retorno de dividendos | I11: 0.006
C12: Investimento Mensal Sugerido (10%) | E12: =E11*0.1 -> 0 | G12: Patrimônio Acumulado | I12: =FV(taxa_mensal,periodo*12,investimento_mensal,0)*-1 -> 0
C13: Investimento Mensal
C14: Por quantos anos?
C17: Carteira Sugerida | G17: Cenários
C19: Tipo de FII | D19: Percentual Sugerido | E19: Valor | G19: Anos | H19: Patrimônio Acumulado | I19: Dividendos
C20: Papel | D20: =VLOOKUP($E$10&"-"&C20,Base!A2:D20,4,FALSE) -> #N/A | E20: =D20*investimento_mensal -> #N/A | G20: 2 | H20: =FV($I$10,G20*12,$E$13,0)*-1 -> 0 | I20: =H20*rendimento_carteira -> 0
C21: Tijolo | D21: =VLOOKUP($E$10&"-"&C21,Base!A3:D21,4,FALSE) -> #N/A | E21: =D21*investimento_mensal -> #N/A | G21: 5 | H21: =FV($I$10,G21*12,$E$13,0)*-1 -> 0 | I21: =H21*rendimento_carteira -> 0
C22: Híbridos | D22: =VLOOKUP($E$10&"-"&C22,Base!A4:D22,4,FALSE) -> #N/A | E22: =D22*investimento_mensal -> #N/A | G22: 10 | H22: =FV($I$10,G22*12,$E$13,0)*-1 -> 0 | I22: =H22*rendimento_carteira -> 0
C23: FOF's | D23: =VLOOKUP($E$10&"-"&C23,Base!A5:D23,4,FALSE) -> #N/A | E23: =D23*investimento_mensal -> #N/A | G23: 20 | H23: =FV($I$10,G23*12,$E$13,0)*-1 -> 0 | I23: =H23*rendimento_carteira -> 0
C24: Desenvolvimento | D24: =VLOOKUP($E$10&"-"&C24,Base!A6:D24,4,FALSE) -> #N/A | E24: =D24*investimento_mensal -> #N/A | G24: 30 | H24: =FV($I$10,G24*12,$E$13,0)*-1 -> 0 | I24: =H24*rendimento_carteira -> 0
C25: Hotelarias | D25: =VLOOKUP($E$10&"-"&C25,Base!A7:D25,4,FALSE) -> #N/A | E25: =D25*investimento_mensal -> #N/A
C26: Total | E26: =SUM(E20:E25) -> #N/A

Sheet Base
A2: Chave | B2: Perfil | C2: Tipo de FII | D2: %
A3: =B3&"-"&C3 -> Conservador-Papel | B3: Conservador | C3: Papel | D3: 0.3
A4: =B4&"-"&C4 -> Conservador-Tijolo | B4: Conservador | C4: Tijolo | D4: 0.5
A5: =B5&"-"&C5 -> Conservador-Híbridos | B5: Conservador | C5: Híbridos | D5: 0.1 | H5: =VLOOKUP(A10,A3:D20,4,FALSE) -> 0.35
A6: =B6&"-"&C6 -> Conservador-FOF's | B6: Conservador | C6: FOF's | D6: 0.1
A7: =B7&"-"&C7 -> Conservador-Desenvolvimento | B7: Conservador | C7: Desenvolvimento | D7: 0
A8: =B8&"-"&C8 -> Conservador-Hotelarias | B8: Conservador | C8: Hotelarias | D8: 0
A9: =B9&"-"&C9 -> Moderado-Papel | B9: Moderado | C9: Papel | D9: 0.32
A10: =B10&"-"&C10 -> Moderado-Tijolo | B10: Moderado | C10: Tijolo | D10: 0.35
A11: =B11&"-"&C11 -> Moderado-Híbridos | B11: Moderado | C11: Híbridos | D11: 0.08
A12: =B12&"-"&C12 -> Moderado-FOF's | B12: Moderado | C12: FOF's | D12: 0.05
A13: =B13&"-"&C13 -> Moderado-Desenvolvimento | B13: Moderado | C13: Desenvolvimento | D13: 0.1
A14: =B14&"-"&C14 -> Moderado-Hotelarias | B14: Moderado | C14: Hotelarias | D14: 0.1
A15: =B15&"-"&C15 -> Agressivo-Papel | B15: Agressivo | C15: Papel | D15: 0.5
A16: =B16&"-"&C16 -> Agressivo-Tijolo | B16: Agressivo | C16: Tijolo | D16: 0.1
A17: =B17&"-"&C17 -> Agressivo-Híbridos | B17: Agressivo | C17: Híbridos | D17: 0.05
... A20: =B20&"-"&C20 -> Agressivo-Hotelarias | B20: Agressivo | C20: Hotelarias | D20: 0.1
